{
  "appInfo" : {
    "build" : "233.13135.93",
    "buildDate" : "2023-12-19T12:38:00Z[UTC]",
    "productCode" : "CL",
    "generated" : "2024-01-24T22:24:30.564074635Z",
    "os" : "Linux 6.7.1-arch1-1",
    "runtime" : "JetBrains s.r.o. 17.0.9 17.0.9+7-b1087.9"
  },
  "runtimeInfo" : {
    "maxMemory" : 2051014656,
    "numberOfProcessors" : 12,
    "maxNumberOfIndexingThreads" : 11,
    "maxSizeOfFileForIntelliSense" : 2560000,
    "maxSizeOfFileForContentLoading" : 20971520
  },
  "type" : "Scanning",
  "projectIndexingActivityHistory" : {
    "projectName" : "Ergos",
    "times" : {
      "scanningReason" : "On project open",
      "scanningType" : "FULL_ON_PROJECT_OPEN",
      "scanningId" : 0,
      "creatingIteratorsTime" : 413056304,
      "concurrentHandlingWallTimeWithoutPauses" : 942759593,
      "concurrentHandlingWallTimeWithPauses" : 942759593,
      "concurrentHandlingSumOfThreadTimesWithPauses" : 1984556278,
      "concurrentIterationAndScannersApplicationSumOfThreadTimesWithPauses" : 255185910,
      "concurrentFileCheckSumOfThreadTimesWithPauses" : 1716529378,
      "delayedPushPropertiesStageTime" : 172951,
      "indexExtensionsTime" : 402625,
      "dumbModeStart" : "2024-01-24T22:24:29.186316359Z",
      "dumbWallTimeWithPauses" : 1372556447,
      "dumbWallTimeWithoutPauses" : 1372556447,
      "updatingStart" : "2024-01-24T22:24:29.175471955Z",
      "updatingEnd" : "2024-01-24T22:24:30.558872806Z",
      "totalWallTimeWithPauses" : 1383391052,
      "wallTimeOnPause" : 0,
      "wasInterrupted" : false,
      "totalWallTimeWithoutPauses" : 1383391052
    },
    "fileCount" : {
      "numberOfFileProviders" : 14,
      "numberOfScannedFiles" : 318,
      "numberOfFilesIndexedByInfrastructureExtensionsDuringScan" : 0,
      "numberOfFilesScheduledForIndexingAfterScan" : 318
    },
    "scanningStatistics" : [ {
      "providerName" : "Indexable set contributor 'com.intellij.javaee.ExternalResourcesRootsProvider@5151d0bd' (non-project)",
      "numberOfScannedFiles" : 212,
      "numberOfSkippedFiles" : 4,
      "numberOfFilesForIndexing" : 212,
      "numberOfFilesFullyIndexedByInfrastructureExtensions" : 0,
      "filesFullyIndexedByInfrastructureExtensions" : [ ],
      "statusTime" : 645306762,
      "totalOneThreadTimeWithPauses" : 844838856,
      "iterationAndScannersApplicationTime" : 141413858,
      "filesCheckTime" : 703321279,
      "timeProcessingUpToDateFiles" : 0,
      "timeUpdatingContentLessIndexes" : 147734632,
      "timeIndexingWithoutContentViaInfrastructureExtension" : 159950,
      "roots" : [ ]
    }, {
      "providerName" : "Indexable set contributor 'JS required libraries' (project)",
      "numberOfScannedFiles" : 90,
      "numberOfSkippedFiles" : 0,
      "numberOfFilesForIndexing" : 90,
      "numberOfFilesFullyIndexedByInfrastructureExtensions" : 0,
      "filesFullyIndexedByInfrastructureExtensions" : [ ],
      "statusTime" : 333603092,
      "totalOneThreadTimeWithPauses" : 370871925,
      "iterationAndScannersApplicationTime" : 4954907,
      "filesCheckTime" : 365846313,
      "timeProcessingUpToDateFiles" : 0,
      "timeUpdatingContentLessIndexes" : 87061010,
      "timeIndexingWithoutContentViaInfrastructureExtension" : 206782,
      "roots" : [ ]
    }, {
      "providerName" : "Indexable set contributor 'TypeScript bundled libraries' (project)",
      "numberOfScannedFiles" : 14,
      "numberOfSkippedFiles" : 69,
      "numberOfFilesForIndexing" : 14,
      "numberOfFilesFullyIndexedByInfrastructureExtensions" : 0,
      "filesFullyIndexedByInfrastructureExtensions" : [ ],
      "statusTime" : 220444465,
      "totalOneThreadTimeWithPauses" : 248982176,
      "iterationAndScannersApplicationTime" : 800950,
      "filesCheckTime" : 248106330,
      "timeProcessingUpToDateFiles" : 0,
      "timeUpdatingContentLessIndexes" : 45365623,
      "timeIndexingWithoutContentViaInfrastructureExtension" : 33701,
      "roots" : [ ]
    }, {
      "providerName" : "Indexable set contributor 'com.intellij.httpClient.http.request.HttpRequestCollectionProvider@66c6d2cf' (non-project)",
      "numberOfScannedFiles" : 2,
      "numberOfSkippedFiles" : 0,
      "numberOfFilesForIndexing" : 2,
      "numberOfFilesFullyIndexedByInfrastructureExtensions" : 0,
      "filesFullyIndexedByInfrastructureExtensions" : [ ],
      "statusTime" : 44160117,
      "totalOneThreadTimeWithPauses" : 187216923,
      "iterationAndScannersApplicationTime" : 13993830,
      "filesCheckTime" : 172771966,
      "timeProcessingUpToDateFiles" : 0,
      "timeUpdatingContentLessIndexes" : 7487069,
      "timeIndexingWithoutContentViaInfrastructureExtension" : 2192,
      "roots" : [ ]
    }, {
      "providerName" : "com.intellij.openapi.roots.ImmutableSyntheticLibrary@7462c1",
      "numberOfScannedFiles" : 0,
      "numberOfSkippedFiles" : 0,
      "numberOfFilesForIndexing" : 0,
      "numberOfFilesFullyIndexedByInfrastructureExtensions" : 0,
      "filesFullyIndexedByInfrastructureExtensions" : [ ],
      "statusTime" : 0,
      "totalOneThreadTimeWithPauses" : 152842140,
      "iterationAndScannersApplicationTime" : 56588965,
      "filesCheckTime" : 94163691,
      "timeProcessingUpToDateFiles" : 0,
      "timeUpdatingContentLessIndexes" : 0,
      "timeIndexingWithoutContentViaInfrastructureExtension" : 0,
      "roots" : [ ]
    }, {
      "providerName" : "Module 'ERGOS' (all roots)",
      "numberOfScannedFiles" : 0,
      "numberOfSkippedFiles" : 0,
      "numberOfFilesForIndexing" : 0,
      "numberOfFilesFullyIndexedByInfrastructureExtensions" : 0,
      "filesFullyIndexedByInfrastructureExtensions" : [ ],
      "statusTime" : 0,
      "totalOneThreadTimeWithPauses" : 42917709,
      "iterationAndScannersApplicationTime" : 27330717,
      "filesCheckTime" : 13334226,
      "timeProcessingUpToDateFiles" : 0,
      "timeUpdatingContentLessIndexes" : 0,
      "timeIndexingWithoutContentViaInfrastructureExtension" : 0,
      "roots" : [ ]
    }, {
      "providerName" : "Indexable set contributor 'org.jetbrains.plugins.scss.index.SassScssIndexedRootProvider@50117907' (non-project)",
      "numberOfScannedFiles" : 0,
      "numberOfSkippedFiles" : 0,
      "numberOfFilesForIndexing" : 0,
      "numberOfFilesFullyIndexedByInfrastructureExtensions" : 0,
      "filesFullyIndexedByInfrastructureExtensions" : [ ],
      "statusTime" : 0,
      "totalOneThreadTimeWithPauses" : 29187668,
      "iterationAndScannersApplicationTime" : 75485,
      "filesCheckTime" : 28974341,
      "timeProcessingUpToDateFiles" : 0,
      "timeUpdatingContentLessIndexes" : 0,
      "timeIndexingWithoutContentViaInfrastructureExtension" : 0,
      "roots" : [ ]
    }, {
      "providerName" : "Indexable set contributor 'Scratches & Consoles' (project)",
      "numberOfScannedFiles" : 0,
      "numberOfSkippedFiles" : 0,
      "numberOfFilesForIndexing" : 0,
      "numberOfFilesFullyIndexedByInfrastructureExtensions" : 0,
      "filesFullyIndexedByInfrastructureExtensions" : [ ],
      "statusTime" : 0,
      "totalOneThreadTimeWithPauses" : 19880246,
      "iterationAndScannersApplicationTime" : 41980,
      "filesCheckTime" : 14256411,
      "timeProcessingUpToDateFiles" : 0,
      "timeUpdatingContentLessIndexes" : 0,
      "timeIndexingWithoutContentViaInfrastructureExtension" : 0,
      "roots" : [ ]
    }, {
      "providerName" : "Indexable set contributor 'Scratches & Consoles' (non-project)",
      "numberOfScannedFiles" : 0,
      "numberOfSkippedFiles" : 0,
      "numberOfFilesForIndexing" : 0,
      "numberOfFilesFullyIndexedByInfrastructureExtensions" : 0,
      "filesFullyIndexedByInfrastructureExtensions" : [ ],
      "statusTime" : 0,
      "totalOneThreadTimeWithPauses" : 19368488,
      "iterationAndScannersApplicationTime" : 7514805,
      "filesCheckTime" : 10300825,
      "timeProcessingUpToDateFiles" : 0,
      "timeUpdatingContentLessIndexes" : 0,
      "timeIndexingWithoutContentViaInfrastructureExtension" : 0,
      "roots" : [ ]
    }, {
      "providerName" : "Indexable set contributor 'com.intellij.javaee.ExternalResourcesRootsProvider@5151d0bd' (project)",
      "numberOfScannedFiles" : 0,
      "numberOfSkippedFiles" : 0,
      "numberOfFilesForIndexing" : 0,
      "numberOfFilesFullyIndexedByInfrastructureExtensions" : 0,
      "filesFullyIndexedByInfrastructureExtensions" : [ ],
      "statusTime" : 0,
      "totalOneThreadTimeWithPauses" : 18044600,
      "iterationAndScannersApplicationTime" : 2207169,
      "filesCheckTime" : 15748501,
      "timeProcessingUpToDateFiles" : 0,
      "timeUpdatingContentLessIndexes" : 0,
      "timeIndexingWithoutContentViaInfrastructureExtension" : 0,
      "roots" : [ ]
    }, {
      "providerName" : "Indexable set contributor 'JS required libraries' (non-project)",
      "numberOfScannedFiles" : 0,
      "numberOfSkippedFiles" : 12,
      "numberOfFilesForIndexing" : 0,
      "numberOfFilesFullyIndexedByInfrastructureExtensions" : 0,
      "filesFullyIndexedByInfrastructureExtensions" : [ ],
      "statusTime" : 0,
      "totalOneThreadTimeWithPauses" : 14123636,
      "iterationAndScannersApplicationTime" : 167197,
      "filesCheckTime" : 13899991,
      "timeProcessingUpToDateFiles" : 0,
      "timeUpdatingContentLessIndexes" : 0,
      "timeIndexingWithoutContentViaInfrastructureExtension" : 0,
      "roots" : [ ]
    }, {
      "providerName" : "Indexable set contributor 'TypeScript bundled libraries' (non-project)",
      "numberOfScannedFiles" : 0,
      "numberOfSkippedFiles" : 0,
      "numberOfFilesForIndexing" : 0,
      "numberOfFilesFullyIndexedByInfrastructureExtensions" : 0,
      "filesFullyIndexedByInfrastructureExtensions" : [ ],
      "statusTime" : 0,
      "totalOneThreadTimeWithPauses" : 13257034,
      "iterationAndScannersApplicationTime" : 15150,
      "filesCheckTime" : 13178344,
      "timeProcessingUpToDateFiles" : 0,
      "timeUpdatingContentLessIndexes" : 0,
      "timeIndexingWithoutContentViaInfrastructureExtension" : 0,
      "roots" : [ ]
    }, {
      "providerName" : "Indexable set contributor 'org.jetbrains.plugins.scss.index.SassScssIndexedRootProvider@50117907' (project)",
      "numberOfScannedFiles" : 0,
      "numberOfSkippedFiles" : 0,
      "numberOfFilesForIndexing" : 0,
      "numberOfFilesFullyIndexedByInfrastructureExtensions" : 0,
      "filesFullyIndexedByInfrastructureExtensions" : [ ],
      "statusTime" : 0,
      "totalOneThreadTimeWithPauses" : 13145064,
      "iterationAndScannersApplicationTime" : 33869,
      "filesCheckTime" : 12907215,
      "timeProcessingUpToDateFiles" : 0,
      "timeUpdatingContentLessIndexes" : 0,
      "timeIndexingWithoutContentViaInfrastructureExtension" : 0,
      "roots" : [ ]
    }, {
      "providerName" : "Indexable set contributor 'com.intellij.httpClient.http.request.HttpRequestCollectionProvider@66c6d2cf' (project)",
      "numberOfScannedFiles" : 0,
      "numberOfSkippedFiles" : 0,
      "numberOfFilesForIndexing" : 0,
      "numberOfFilesFullyIndexedByInfrastructureExtensions" : 0,
      "filesFullyIndexedByInfrastructureExtensions" : [ ],
      "statusTime" : 0,
      "totalOneThreadTimeWithPauses" : 9879813,
      "iterationAndScannersApplicationTime" : 47028,
      "filesCheckTime" : 9719945,
      "timeProcessingUpToDateFiles" : 0,
      "timeUpdatingContentLessIndexes" : 0,
      "timeIndexingWithoutContentViaInfrastructureExtension" : 0,
      "roots" : [ ]
    } ]
  }
}